sbscorer/__init__.py
sbscorer/sbdata/FlipsideApi.py
sbscorer/sbdata/__init__.py
sbscorer/sblegos/FeatureCreator.py
sbscorer/sblegos/Transaction.py
sbscorer/sblegos/TransactionAnalyser.py
sbscorer/sblegos/TransactionAnalyserTest.py
sbscorer/sblegos/__init__.py
sbscorer/sblegos/features/__init__.py
sbscorer/sblegos/features/conf.py
sbscorer/sblegos/features/create_features.py
sbscorer/sblegos/features/custom/__init__.py
sbscorer/sblegos/features/custom/extract.py
sbscorer/sbutils/LoadData.py
sbscorer/sbutils/__init__.py
sybil_scorer-0.4.0.dist-info/LICENSE
sybil_scorer-0.4.0.dist-info/METADATA
sybil_scorer-0.4.0.dist-info/WHEEL
sybil_scorer-0.4.0.dist-info/top_level.txt
sybil_scorer-0.4.0.dist-info/RECORD
