Metadata-Version: 2.1
Name: sybil-scorer
Version: 0.4.0
Summary: A sybil scoring tool
Author-email: Poupou <poupou-web3@protonmail.com>
License: MIT License
Project-URL: Homepage, https://github.com/poupou-web3/sybil-scorer
Project-URL: Documentation, https://sybil-scorer.readthedocs.io/en/latest/py-modindex.html
Keywords: Sybil,OSS,Gitcoin,Quadratic,OpenData Community,ODC
Classifier: License :: OSI Approved :: MIT License
Classifier: Programming Language :: Python
Classifier: Programming Language :: Python :: 3
Requires-Python: >=3.9
License-File: LICENSE
Requires-Dist: pandas >=2.0.2
Requires-Dist: flipside >=2.0.7
Requires-Dist: tsfresh >=0.20.1
Requires-Dist: pylcs ==0.0.8
Requires-Dist: tomli ; python_version < "3.11"
Provides-Extra: dev
Requires-Dist: black ; extra == 'dev'
Requires-Dist: jupyterlab ==3.5.2 ; extra == 'dev'
Requires-Dist: ipykernel ==6.20.2 ; extra == 'dev'
Requires-Dist: pip-tools ; extra == 'dev'
Requires-Dist: pytest ==7.2.1 ; extra == 'dev'
